cisa_kev/__init__.py
cisa_kev/__main__.py
cisa_kev/cli.py
cisa_kev/client.py
cisa_kev/util.py
cisa_kev-2.0.1.dist-info/METADATA
cisa_kev-2.0.1.dist-info/WHEEL
cisa_kev-2.0.1.dist-info/entry_points.txt
cisa_kev-2.0.1.dist-info/RECORD
