Metadata-Version: 2.1
Name: cisa-kev
Version: 2.0.1
Summary: A wildly opinionated client for the CISA Known Exploited Vulnerabilities (KEV) catalog
License: MIT
Author: Tyler Fisher
Author-email: tylerfisher@tylerfisher.ca
Requires-Python: >=3.10,<4.0
Classifier: License :: OSI Approved :: MIT License
Classifier: Programming Language :: Python :: 3
Classifier: Programming Language :: Python :: 3.10
Classifier: Programming Language :: Python :: 3.11
Classifier: Programming Language :: Python :: 3.12
Requires-Dist: click (>=8.1.7,<9.0.0)
Requires-Dist: pandas (>=2.2.0,<3.0.0)
Requires-Dist: polars (>=0.20.6,<0.21.0)
Requires-Dist: requests (>=2.31.0,<3.0.0)
